oscurl/__init__.py
oscurl/oscurl.py
oscurl/tests/__init__.py
oscurl/tests/test_oscurl.py
oscurl-1.1.1.dist-info/DESCRIPTION.rst
oscurl-1.1.1.dist-info/METADATA
oscurl-1.1.1.dist-info/RECORD
oscurl-1.1.1.dist-info/WHEEL
oscurl-1.1.1.dist-info/entry_points.txt
oscurl-1.1.1.dist-info/metadata.json
oscurl-1.1.1.dist-info/pbr.json
oscurl-1.1.1.dist-info/top_level.txt
