Metadata-Version: 2.0
Name: oscurl
Version: 1.1.1
Summary: cURL-like tool to access OpenStack APIs with keystone auth
Home-page: https://github.com/yosshy/oscurl
Author: Akira Yoshiyama, Akihiro Motoki
Author-email: akirayoshiyama@gmail.com
License: Apache-2
Platform: UNKNOWN
Classifier: Environment :: OpenStack
Classifier: Intended Audience :: Information Technology
Classifier: Intended Audience :: System Administrators
Classifier: License :: OSI Approved :: Apache Software License
Classifier: Operating System :: POSIX :: Linux
Classifier: Programming Language :: Python
Classifier: Programming Language :: Python :: 2
Classifier: Programming Language :: Python :: 2.7
Classifier: Programming Language :: Python :: 3
Classifier: Programming Language :: Python :: 3.5
Requires-Dist: PyYAML
Requires-Dist: os-client-config (>=1.13.0)
